pydantic_requests/__init__.py
pydantic_requests-0.1.4.dist-info/LICENSE
pydantic_requests-0.1.4.dist-info/WHEEL
pydantic_requests-0.1.4.dist-info/METADATA
pydantic_requests-0.1.4.dist-info/RECORD
