Metadata-Version: 2.1
Name: pydantic-requests
Version: 0.1.4
Summary: A pydantic integration with requests.
Home-page: https://github.com/dz0ny/pydantic-requests
License: MIT
Author: Janez Troha
Author-email: dz0ny@ubuntu.si
Requires-Python: >=3.7,<4.0
Classifier: License :: OSI Approved :: MIT License
Classifier: Programming Language :: Python :: 3
Classifier: Programming Language :: Python :: 3.10
Classifier: Programming Language :: Python :: 3.7
Classifier: Programming Language :: Python :: 3.8
Classifier: Programming Language :: Python :: 3.9
Requires-Dist: pydantic (>=0.25.0)
Requires-Dist: requests (>=2.21)
Project-URL: Repository, https://github.com/dz0ny/pydantic-requests
